morethon/__init__.py
morethon/__main__.py
morethon/__version__.py
morethon/_typing.py
morethon/_version.py
morethon/core.py
morethon/error.py
morethon/grammar.py
morethon/tokenize.py
morethon-0.0.0.dist-info/METADATA
morethon-0.0.0.dist-info/WHEEL
morethon-0.0.0.dist-info/entry_points.txt
morethon-0.0.0.dist-info/licenses/LICENSE
morethon-0.0.0.dist-info/RECORD
